finwell_analyzer/__init__.py
finwell_analyzer/main.py
finwell_analyzer/prompts.py
finwell_analyzer-2025.12.21103304.dist-info/METADATA
finwell_analyzer-2025.12.21103304.dist-info/WHEEL
finwell_analyzer-2025.12.21103304.dist-info/top_level.txt
finwell_analyzer-2025.12.21103304.dist-info/RECORD
