Metadata-Version: 2.4
Name: finwell-analyzer
Version: 2025.12.21103304
Summary: A new package designed to analyze user-submitted texts related to financial well-being by employing language models and pattern matching. The package processes the input to identify key sentiments, th
Author-email: finwell-analyzer <hi@eugene.plus>
License: MIT
Project-URL: Homepage, https://github.com/chigwell/finwell-analyzer
Requires-Python: >=3.9
Requires-Dist: langchain-llm7>=0.0.0
Requires-Dist: llmatch-messages>=0.0.0
Requires-Dist: langchain-core>=0.3.0
